houtu/__init__.py
houtu/geocoding.py
houtu/utils.py
houtu/data/cities1000.txt.xz
houtu-0.0.3.dist-info/LICENSE
houtu-0.0.3.dist-info/WHEEL
houtu-0.0.3.dist-info/METADATA
houtu-0.0.3.dist-info/RECORD
