Metadata-Version: 2.1
Name: houtu
Version: 0.0.3
Summary: Offline fast reverse geocoding. Named after the Chinese Goddess of the Earth Houtu.
Author-email: Dobatymo <dobatymo@users.noreply.github.com>
Requires-Python: >=3.8
Classifier: Intended Audience :: Developers
Classifier: License :: OSI Approved :: MIT License
Classifier: Programming Language :: Python :: 3 :: Only
Classifier: Programming Language :: Python :: 3.8
Classifier: Programming Language :: Python :: 3.9
Classifier: Programming Language :: Python :: 3.10
Classifier: Programming Language :: Python :: 3.11
Classifier: Programming Language :: Python :: 3.12
Classifier: Topic :: Scientific/Engineering :: GIS
Requires-Dist: importlib-resources
Requires-Dist: numpy
Requires-Dist: scikit-learn
Requires-Dist: scipy>=1.6
Requires-Dist: geopy ; extra == "optimize"
Requires-Dist: pymap3d ; extra == "optimize"
Requires-Dist: pynear>=0.1 ; extra == "optional"
Requires-Dist: vptree>=1.3 ; extra == "optional"
Requires-Dist: genutility[cache] ; extra == "test"
Project-URL: Home, https://github.com/Dobatymo/houtu
Provides-Extra: optimize
Provides-Extra: optional
Provides-Extra: test
